qlever/__init__.py
qlever/command.py
qlever/config.py
qlever/containerize.py
qlever/log.py
qlever/qlever_main.py
qlever/qleverfile.py
qlever/util.py
qlever/Qleverfiles/Qleverfile.dblp
qlever/Qleverfiles/Qleverfile.dblp-plus
qlever/Qleverfiles/Qleverfile.dbpedia
qlever/Qleverfiles/Qleverfile.default
qlever/Qleverfiles/Qleverfile.dnb
qlever/Qleverfiles/Qleverfile.fbeasy
qlever/Qleverfiles/Qleverfile.freebase
qlever/Qleverfiles/Qleverfile.imdb
qlever/Qleverfiles/Qleverfile.ohm-planet
qlever/Qleverfiles/Qleverfile.olympics
qlever/Qleverfiles/Qleverfile.orkg
qlever/Qleverfiles/Qleverfile.osm-country
qlever/Qleverfiles/Qleverfile.osm-planet
qlever/Qleverfiles/Qleverfile.osm-planet-from-pbf
qlever/Qleverfiles/Qleverfile.pubchem
qlever/Qleverfiles/Qleverfile.scientists
qlever/Qleverfiles/Qleverfile.uniprot
qlever/Qleverfiles/Qleverfile.vvz
qlever/Qleverfiles/Qleverfile.wikidata
qlever/Qleverfiles/Qleverfile.wikipathways
qlever/Qleverfiles/Qleverfile.yago-4
qlever/commands/__init__.py
qlever/commands/add_text_index.py
qlever/commands/benchmark_queries.py
qlever/commands/cache_stats.py
qlever/commands/clear_cache.py
qlever/commands/extract_queries.py
qlever/commands/get_data.py
qlever/commands/index.py
qlever/commands/index_stats.py
qlever/commands/log.py
qlever/commands/materialized_view.py
qlever/commands/query.py
qlever/commands/rebuild_index.py
qlever/commands/reset_updates.py
qlever/commands/settings.py
qlever/commands/setup_config.py
qlever/commands/start.py
qlever/commands/status.py
qlever/commands/stop.py
qlever/commands/system_info.py
qlever/commands/ui.py
qlever/commands/update.py
qlever/commands/update_wikidata.py
qlever/commands/warmup.py
qlever-0.5.42.dist-info/licenses/LICENSE
qlever-0.5.42.dist-info/METADATA
qlever-0.5.42.dist-info/WHEEL
qlever-0.5.42.dist-info/entry_points.txt
qlever-0.5.42.dist-info/top_level.txt
qlever-0.5.42.dist-info/RECORD
