Metadata-Version: 2.4
Name: qlever
Version: 0.5.42
Summary: Command-line tool for using the QLever graph database
Author-email: Hannah Bast <bast@cs.uni-freiburg.de>
License-Expression: Apache-2.0
Project-URL: homepage, https://github.com/ad-freiburg/qlever
Project-URL: documentation, https://docs.qlever.dev
Project-URL: repository, https://github.com/ad-freiburg/qlever.git
Project-URL: bugtracker, https://github.com/ad-freiburg/qlever/issues
Keywords: Graph database,Triplestore,Knowledge graphs,SPARQL,RDF
Classifier: Topic :: Database :: Database Engines/Servers
Classifier: Topic :: Database :: Front-Ends
Requires-Python: >=3.8
License-File: LICENSE
Requires-Dist: psutil
Requires-Dist: termcolor
Requires-Dist: argcomplete
Requires-Dist: pyyaml
Requires-Dist: rdflib
Requires-Dist: requests-sse
Requires-Dist: tqdm
Dynamic: license-file
